{
	"$schema": "https://turborepo.org/schema.json",
	"globalDependencies": ["**/.env"],
	"ui": "stream",
	"tasks": {
		"topo": {
			"dependsOn": ["^topo"]
		},
		"build": {
			"dependsOn": ["^build"],
			"inputs": ["$TURBO_DEFAULT$", ".env*"],
			"outputs": ["dist/**"]
		},
		"lint": {
			"dependsOn": ["^lint"]
		},
		"clean": {
			"cache": false
		},
		"check-types": {
			"dependsOn": ["^check-types"]
		},
		"dev": {
			"inputs": ["$TURBO_DEFAULT$", ".env"],
			"cache": false,
			"persistent": true
		},
		"db:push": {
			"cache": false,
			"persistent": true
		},
		"db:studio": {
			"cache": false,
			"persistent": true
		},
		"db:migrate": {
			"cache": false,
			"persistent": true
		},
		"db:generate": {
			"cache": false,
			"persistent": true
		}
	}
}
